evmchains/__init__.py
evmchains/chains.py
evmchains/py.typed
evmchains/types.py
evmchains/version.py
evmchains-0.1.6.dist-info/licenses/LICENSE
evmchains-0.1.6.dist-info/METADATA
evmchains-0.1.6.dist-info/WHEEL
evmchains-0.1.6.dist-info/top_level.txt
evmchains-0.1.6.dist-info/RECORD
