Metadata-Version: 2.4
Name: evmchains
Version: 0.1.6
Summary: Packaged metadata on Ethereum Virtual Machine (EVM) chains
Author-email: ApeWorX <admin@apeworx.io>
License-Expression: Apache-2.0
Project-URL: Homepage, https://github.com/ApeWorX/evmchains
Project-URL: Documentation, https://github.com/ApeWorX/evmchains#readme
Project-URL: Issues, https://github.com/ApeWorX/evmchains/issues
Project-URL: Source, https://github.com/ApeWorX/evmchains
Keywords: ethereum,evm,blockchain
Classifier: Development Status :: 5 - Production/Stable
Classifier: Intended Audience :: Developers
Classifier: Natural Language :: English
Classifier: Operating System :: MacOS
Classifier: Operating System :: POSIX
Classifier: Operating System :: Microsoft :: Windows
Classifier: Programming Language :: Python :: 3
Classifier: Programming Language :: Python :: 3.10
Classifier: Programming Language :: Python :: 3.11
Classifier: Programming Language :: Python :: 3.12
Classifier: Programming Language :: Python :: 3.13
Classifier: Programming Language :: Python :: 3.14
Requires-Python: >=3.10
License-File: LICENSE
Requires-Dist: pydantic<3,>=2.5.3
Dynamic: license-file
